keyszer/__init__.py
keyszer/cli.py
keyszer/config_api.py
keyszer/input.py
keyszer/output.py
keyszer/transform.py
keyszer/version.py
keyszer/xorg.py
keyszer/lib/__init__.py
keyszer/lib/benchit.py
keyszer/lib/key_context.py
keyszer/lib/logger.py
keyszer/models/__init__.py
keyszer/models/action.py
keyszer/models/combo.py
keyszer/models/key.py
keyszer/models/keymap.py
keyszer/models/keystate.py
keyszer/models/modifier.py
keyszer/models/modmap.py
keyszer-0.6.0.dist-info/METADATA
keyszer-0.6.0.dist-info/WHEEL
keyszer-0.6.0.dist-info/entry_points.txt
keyszer-0.6.0.dist-info/license_files/LICENSE
keyszer-0.6.0.dist-info/RECORD
