Metadata-Version: 2.1
Name: keyszer
Version: 0.6.0
Summary: A smart, flexible keymapper for Linux.
Project-URL: Bug-tracker, https://github.com/jgoebel/keyszer/issues
Project-URL: Home-page, https://github.com/jgoebel/keyszer
Maintainer-email: Josh Goebel <hello@joshgoebel.com>
License: GNU General Public License v3.0 or later
Keywords: keymapper
Classifier: Development Status :: 4 - Beta
Classifier: License :: OSI Approved :: GNU General Public License v3 or later (GPLv3+)
Classifier: Operating System :: POSIX :: Linux
Classifier: Programming Language :: Python :: 3
Requires-Python: >=3.6
Requires-Dist: appdirs~=1.4
Requires-Dist: evdev~=1.5
Requires-Dist: inotify-simple~=1.3
Requires-Dist: ordered-set~=4.1
Requires-Dist: python-xlib==0.31
Provides-Extra: dev
Requires-Dist: looptime; extra == 'dev'
Requires-Dist: pytest; extra == 'dev'
Requires-Dist: pytest-asyncio; extra == 'dev'
Requires-Dist: toml; extra == 'dev'
